SuperSubCap/__init__.py
SuperSubCap-0.0.5.dist-info/LICENCE.txt
SuperSubCap-0.0.5.dist-info/METADATA
SuperSubCap-0.0.5.dist-info/WHEEL
SuperSubCap-0.0.5.dist-info/top_level.txt
SuperSubCap-0.0.5.dist-info/RECORD
