Metadata-Version: 2.1
Name: SuperSubCap
Version: 0.0.5
Summary: Superscripts and subscripts for latin and greek letters, numbers and operands
Home-page: https://github.com/Dryhb/SuperSubCap_library
Author: Dryhb
Author-email: dryhb.pseudotooshort@gmail.com
License: MIT
Keywords: latin greek subscripts superscripts caps letters
Classifier: Development Status :: 5 - Production/Stable
Classifier: Intended Audience :: Education
Classifier: Operating System :: Microsoft :: Windows :: Windows 10
Classifier: License :: OSI Approved :: MIT License
Classifier: Programming Language :: Python :: 3
License-File: LICENCE.txt
